q3net/__init__.py
q3net/clientstate.py
q3net/defines.py
q3net/engine.py
q3net/mkcrc.py
q3net/packets.py
q3net/protocol.py
q3net/utils.py
q3net-1.0.1.dist-info/METADATA
q3net-1.0.1.dist-info/WHEEL
q3net-1.0.1.dist-info/top_level.txt
q3net-1.0.1.dist-info/RECORD
