Metadata-Version: 2.1
Name: q3net
Version: 1.0.1
Summary: Quake 3 connection emulator
Home-page: https://github.com/JKornev/q3net
Author: JKornev
License: Free
Requires-Dist: q3huff2 (==0.4.2)
